configfacets/__init__.py
configfacets/main.py
configfacets/server.py
configfacets_mcp-0.0.2.dist-info/METADATA
configfacets_mcp-0.0.2.dist-info/WHEEL
configfacets_mcp-0.0.2.dist-info/top_level.txt
configfacets_mcp-0.0.2.dist-info/RECORD
