Metadata-Version: 2.4
Name: configfacets-mcp
Version: 0.0.2
Summary: Add your description here
Requires-Python: >=3.13
Requires-Dist: mcp[cli]>=1.6.0
